scelephant/__init__.py
scelephant/__main__.py
scelephant/core/BA.py
scelephant/core/STR.py
scelephant/core/__init__.py
scelephant/core/biobookshelf.py
scelephant/core/core.py
scelephant/core/misc.py
scelephant/core/utils.py
scelephant/utils/__init__.py
scelephant/utils/utils.py
scelephant-0.2.7.dist-info/LICENSE
scelephant-0.2.7.dist-info/METADATA
scelephant-0.2.7.dist-info/WHEEL
scelephant-0.2.7.dist-info/top_level.txt
scelephant-0.2.7.dist-info/RECORD
