Metadata-Version: 2.1
Name: scelephant
Version: 0.2.7
Summary: SC-Elephant (Single-Cell Extremely Large Data Analysis Platform)
Home-page: https://github.com/ahs2202/scelephant
Author: Hyunsu An
Author-email: ahs2202@gm.gist.ac.kr
License: MIT
Requires-Python: >=3.8
License-File: LICENSE
Requires-Dist: managed-file-system-operator >=0.0.1
Requires-Dist: zarr >=2.16.0
Requires-Dist: fsspec >=2023.6.0
Requires-Dist: s3fs >=2023.6.0
Requires-Dist: numcodecs >=0.9.1
Requires-Dist: bitarray >=2.4.1
Requires-Dist: scanpy >=1.9.1
Requires-Dist: tqdm >=4.64.0
Requires-Dist: pynndescent >=0.5.7
Requires-Dist: scipy >=1.7.3
Requires-Dist: numba >=0.55.2
Requires-Dist: hdbscan >=0.8.28
Requires-Dist: leidenalg >=0.8.10
Requires-Dist: igraph >=0.9.11
Requires-Dist: h5py >=3.8.0
